LICENSE.txt
MANIFEST.in
README.rst
setup.py
tebe/__init__.py
tebe/__main__.py
tebe.egg-info/PKG-INFO
tebe.egg-info/SOURCES.txt
tebe.egg-info/dependency_links.txt
tebe.egg-info/entry_points.txt
tebe.egg-info/requires.txt
tebe.egg-info/top_level.txt
tebe/examples/__init__.py
tebe/examples/biohazard.png
tebe/examples/example_1.rst
tebe/examples/example_2.rst
tebe/examples/example_3.rst
tebe/examples/image.png
tebe/gui/Editor.py
tebe/gui/Preview.py
tebe/gui/Tree.py
tebe/gui/__init__.py
tebe/icons/__init__.py
tebe/icons/about.png
tebe/icons/auto.png
tebe/icons/build.png
tebe/icons/edit.png
tebe/icons/help.png
tebe/icons/index.png
tebe/icons/logo.png
tebe/icons/new.png
tebe/icons/open_file.png
tebe/icons/open_folder.png
tebe/icons/pdf_sphinx.png
tebe/icons/pdf_this.png
tebe/icons/print.png
tebe/icons/quit.png
tebe/icons/refresh_preview.png
tebe/icons/save.png
tebe/icons/save_as.png
tebe/icons/scroll.png
tebe/icons/theme.png
tebe/info/__init__.py
tebe/info/appdata.py
tebe/pycore/Content.py
tebe/pycore/Document.py
tebe/pycore/Environment.py
tebe/pycore/Rst2PdfBuilder.py
tebe/pycore/SphinxBuilder.py
tebe/pycore/__init__.py
tebe/pycore/app_utils.py
tebe/pycore/create_index_content.py
tebe/pycore/help_content.py
tebe/pycore/markup_utils.py
tebe/pycore/rst2pdf_conf_template/__init__.py
tebe/pycore/sphinx_conf_template/__init__.py
tebe/pycore/sphinx_conf_template/conf_base.py
tebe/pycore/sphinx_conf_template/conf_tebe_custom.py
tebe/pycore/sphinx_conf_template/basic_like_paper/__init__.py
tebe/pycore/sphinx_conf_template/basic_like_paper/conf.py
tebe/pycore/sphinx_conf_template/classic_like_web/__init__.py
tebe/pycore/sphinx_conf_template/classic_like_web/conf.py
tebe/pycore/sphinx_conf_template/sphinxdoc_like_web/__init__.py
tebe/pycore/sphinx_conf_template/sphinxdoc_like_web/conf.py