Metadata-Version: 2.1
Name: tebe
Version: 0.2.8
Summary: Tebe is a simple but powerful editor for Markdown and reStructuredText markup languages with Sphinx and Rst2Pdf power included
Home-page: https://tebe.readthedocs.io
Author: Lukasz Laba
Author-email: lukaszlaba@gmail.com.pl
License: GNU General Public License (GPL)
Keywords: sphinx,restructuredtext,markdown,markup
Classifier: Development Status :: 4 - Beta
Classifier: Environment :: X11 Applications :: Qt
Classifier: Intended Audience :: End Users/Desktop
Classifier: License :: OSI Approved :: GNU General Public License (GPL)
Classifier: Operating System :: POSIX :: Linux
Classifier: Operating System :: Microsoft :: Windows
Classifier: Programming Language :: Python
Classifier: Topic :: Scientific/Engineering
Classifier: Topic :: Documentation :: Sphinx
Classifier: Topic :: Office/Business
Classifier: Topic :: Text Editors
Requires-Python: >3
License-File: LICENSE.txt
